odoo/addons/sale_product_set_packaging_qty/README.rst
odoo/addons/sale_product_set_packaging_qty/__init__.py
odoo/addons/sale_product_set_packaging_qty/__manifest__.py
odoo/addons/sale_product_set_packaging_qty/i18n/sale_product_set_packaging_qty.pot
odoo/addons/sale_product_set_packaging_qty/models/__init__.py
odoo/addons/sale_product_set_packaging_qty/models/product_set.py
odoo/addons/sale_product_set_packaging_qty/readme/CONTRIBUTORS.rst
odoo/addons/sale_product_set_packaging_qty/readme/DESCRIPTION.rst
odoo/addons/sale_product_set_packaging_qty/static/description/icon.png
odoo/addons/sale_product_set_packaging_qty/static/description/index.html
odoo/addons/sale_product_set_packaging_qty/tests/__init__.py
odoo/addons/sale_product_set_packaging_qty/tests/test_product_set_packaging.py
odoo/addons/sale_product_set_packaging_qty/views/product_set.xml
odoo13_addon_sale_product_set_packaging_qty-13.0.1.0.1.dist-info/METADATA
odoo13_addon_sale_product_set_packaging_qty-13.0.1.0.1.dist-info/WHEEL
odoo13_addon_sale_product_set_packaging_qty-13.0.1.0.1.dist-info/top_level.txt
odoo13_addon_sale_product_set_packaging_qty-13.0.1.0.1.dist-info/RECORD
