Metadata-Version: 2.1
Name: odoo13-addon-sale-product-set-packaging-qty
Version: 13.0.1.0.1
Summary: Manage packaging and quantities on product set lines
Home-page: https://github.com/OCA/sale-workflow
Author: Camptocamp, Odoo Community Association (OCA)
Author-email: support@odoo-community.org
License: AGPL-3
Platform: UNKNOWN
Classifier: Programming Language :: Python
Classifier: Framework :: Odoo
Classifier: License :: OSI Approved :: GNU Affero General Public License v3
Classifier: Development Status :: 3 - Alpha
Requires-Python: >=3.5
Requires-Dist: odoo13-addon-sale-product-set
Requires-Dist: odoo (<13.1dev,>=13.0a)
